antibot/__init__.py
antibot/decorators.py
antibot/main.py
antibot/plugin.py
antibot/provided.py
antibot/tools.py
antibot/user.py
antibot/internal/__init__.py
antibot/internal/configuration.py
antibot/internal/module.py
antibot/internal/plugins.py
antibot/internal/scheduler.py
antibot/internal/backend/__init__.py
antibot/internal/backend/command_runner.py
antibot/internal/backend/constants.py
antibot/internal/backend/debugger.py
antibot/internal/backend/descriptor.py
antibot/internal/backend/endpoint_runner.py
antibot/internal/backend/installer.py
antibot/internal/backend/request_checker.py
antibot/internal/backend/ws_runner.py
antibot/internal/backend/actions/__init__.py
antibot/internal/backend/actions/action_runner.py
antibot/internal/backend/actions/block_action_runner.py
antibot/internal/backend/actions/view_closed_runner.py
antibot/internal/backend/actions/view_submit_runner.py
antibot/internal/slack/__init__.py
antibot/internal/slack/channel.py
antibot/internal/slack/upload.py
antibot/internal/slack/user.py
antibot/repository/__init__.py
antibot/repository/messages.py
antibot/repository/users.py
antibot/slack/__init__.py
antibot/slack/api.py
antibot/slack/callback.py
antibot/slack/message.py
antibot-2.1.7.dist-info/licenses/LICENSE
antibot-2.1.7.dist-info/METADATA
antibot-2.1.7.dist-info/WHEEL
antibot-2.1.7.dist-info/entry_points.txt
antibot-2.1.7.dist-info/top_level.txt
antibot-2.1.7.dist-info/RECORD
