Metadata-Version: 2.4
Name: antibot
Version: 2.1.7
Author: Jean Giard
License: LGPL
License-File: LICENSE
Requires-Dist: pymongo
Requires-Dist: requests
Requires-Dist: injector
Requires-Dist: pyckson
Requires-Dist: pytz
Requires-Dist: schedule
Requires-Dist: slack_sdk
Requires-Dist: arrow
Requires-Dist: bottle
Dynamic: author
Dynamic: license
Dynamic: license-file
Dynamic: requires-dist
